setup.py
dsnd_probability_ts/Binomialdistribution.py
dsnd_probability_ts/Gaussiandistribution.py
dsnd_probability_ts/Generaldistribution.py
dsnd_probability_ts/__init__.py
dsnd_probability_ts.egg-info/PKG-INFO
dsnd_probability_ts.egg-info/SOURCES.txt
dsnd_probability_ts.egg-info/dependency_links.txt
dsnd_probability_ts.egg-info/not-zip-safe
dsnd_probability_ts.egg-info/top_level.txt